README.md
setup.py
poesy/__init__.py
poesy/poesy.py
poesy.egg-info/PKG-INFO
poesy.egg-info/SOURCES.txt
poesy.egg-info/dependency_links.txt
poesy.egg-info/requires.txt
poesy.egg-info/top_level.txt
poesy/schemes/rhyme_schemes.txt