Metadata-Version: 2.1
Name: poesy
Version: 0.3.1
Summary: Poetic processing, for Python
Home-page: https://github.com/quadrismegistus/poesy
Author: Ryan Heuser
Author-email: heuser@stanford.edu
License: MPL-2.0
Platform: UNKNOWN
